neqsimapi_connector/__init__.py
neqsimapi_connector/connector.py
neqsimapi_connector-1.1.2.dist-info/METADATA
neqsimapi_connector-1.1.2.dist-info/WHEEL
neqsimapi_connector-1.1.2.dist-info/RECORD
