Metadata-Version: 2.3
Name: neqsimapi-connector
Version: 1.1.2
Summary: A python package to simplify calling NeqSimAPI for end-users.
License: MIT
Author: Åsmund Våge Fannemel
Author-email: asmf@equinor.com
Requires-Python: >=3.9.2,<4.0.0
Classifier: License :: OSI Approved :: MIT License
Classifier: Programming Language :: Python :: 3
Classifier: Programming Language :: Python :: 3.10
Classifier: Programming Language :: Python :: 3.11
Classifier: Programming Language :: Python :: 3.12
Classifier: Programming Language :: Python :: 3.13
Requires-Dist: httpx (>=0.28.1,<0.29.0)
Requires-Dist: msal_bearer (>=1.3.0,<2.0.0)
Project-URL: Repository, https://github.com/equinor/NeqSimAPI-connector
